LICENSE.txt
README.md
setup.py
app/automated_cutoff.py
app/dracoon.py
app/dracoon_app.py
app/utils.py
dracoonpy.egg-info/PKG-INFO
dracoonpy.egg-info/SOURCES.txt
dracoonpy.egg-info/dependency_links.txt
dracoonpy.egg-info/requires.txt
dracoonpy.egg-info/top_level.txt