Metadata-Version: 2.1
Name: dracoonpy
Version: 0.1.3
Summary: DRaCOoN (Differential Regulation and CO-expression Networks) is a data-driven tool optimized for effectively retrieving differential relationships between genes across two distinct conditions. 
Home-page: https://github.com/fmdelgado/DRACOONpy
Author: Fernando M. Delgado Chaves, PhD
Author-email: fernando.miguel.delgado-chaves@uni-hamburg.de
Classifier: Programming Language :: Python :: 3.10
Classifier: Intended Audience :: Science/Research
Requires-Python: >=3.10
License-File: LICENSE.txt
